meta_learning/__init__.py
meta_learning/cli.py
meta_learning/meta_learning_modules/__init__.py
meta_learning/meta_learning_modules/continual_meta_learning.py
meta_learning/meta_learning_modules/few_shot_learning.py
meta_learning/meta_learning_modules/maml_variants.py
meta_learning/meta_learning_modules/test_time_compute.py
meta_learning/meta_learning_modules/utils.py
meta_learning_benedictchen-1.0.1.dist-info/METADATA
meta_learning_benedictchen-1.0.1.dist-info/WHEEL
meta_learning_benedictchen-1.0.1.dist-info/entry_points.txt
meta_learning_benedictchen-1.0.1.dist-info/licenses/LICENSE
meta_learning_benedictchen-1.0.1.dist-info/RECORD
