Metadata-Version: 2.4
Name: meta-learning-benedictchen
Version: 1.0.1
Summary: Advanced meta-learning algorithms including test-time compute scaling, MAML variants, and few-shot learning
Project-URL: Funding, https://www.paypal.com/cgi-bin/webscr?cmd=_s-xclick&hosted_button_id=WXQKYYKPHWXHS
Project-URL: Sponsor, https://github.com/sponsors/benedictchen
Author-email: Benedict Chen <benedict@benedictchen.com>
Maintainer-email: Benedict Chen <benedict@benedictchen.com>
License: Custom Non-Commercial License with Donation Requirements
License-File: LICENSE
Requires-Python: >=3.9
Requires-Dist: matplotlib>=3.5.0
Requires-Dist: numpy>=1.21.0
Requires-Dist: scikit-learn>=1.0.0
Requires-Dist: scipy>=1.7.0
Requires-Dist: torch>=2.0.0
Requires-Dist: tqdm>=4.64.0
Requires-Dist: transformers>=4.20.0
Provides-Extra: llm
Requires-Dist: accelerate>=0.20.0; extra == 'llm'
Requires-Dist: datasets>=2.10.0; extra == 'llm'
Requires-Dist: openai>=1.0.0; extra == 'llm'
Provides-Extra: research
Requires-Dist: higher>=0.2.1; extra == 'research'
Requires-Dist: learn2learn>=0.1.7; extra == 'research'
Requires-Dist: torchmeta>=1.8.0; extra == 'research'
Provides-Extra: test
Requires-Dist: pytest-cov>=4.0; extra == 'test'
Requires-Dist: pytest>=7.0; extra == 'test'
